jaylib/__init__.py
jaylib/function.py
jaylib-0.0.1.dist-info/LICENSE
jaylib-0.0.1.dist-info/METADATA
jaylib-0.0.1.dist-info/WHEEL
jaylib-0.0.1.dist-info/top_level.txt
jaylib-0.0.1.dist-info/RECORD
