Metadata-Version: 2.1
Name: jaylib
Version: 0.0.1
Summary: Shared code
Home-page: UNKNOWN
Author: itsjaylen
Author-email: bossjaylen145@gmail.com
License: UNKNOWN
Keywords: lib
Platform: UNKNOWN
Classifier: Development Status :: 1 - Planning
Classifier: Intended Audience :: Developers
Classifier: Programming Language :: Python :: 3
Classifier: Operating System :: Unix
Classifier: Operating System :: MacOS :: MacOS X
Classifier: Operating System :: Microsoft :: Windows
License-File: LICENSE
